sdwis_drink_water/.DS_Store
sdwis_drink_water/__init__.py
sdwis_drink_water/api.py
sdwis_drink_water/api_for_table.py
sdwis_drink_water/configs.py
sdwis_drink_water/data_praser.py
sdwis_drink_water/errors.py
sdwis_drink_water/models/__init__.py
sdwis_drink_water/models/_auto_making_models_file_script.py
sdwis_drink_water/models/_auto_making_models_file_script_no_region_id.py
sdwis_drink_water/models/enforcement_action.py
sdwis_drink_water/models/geographic_area.py
sdwis_drink_water/models/lcr_sample.py
sdwis_drink_water/models/lcr_sample_result.py
sdwis_drink_water/models/service_area.py
sdwis_drink_water/models/treatment.py
sdwis_drink_water/models/violation.py
sdwis_drink_water/models/violation_enf_assoc.py
sdwis_drink_water/models/water_system.py
sdwis_drink_water/models/water_system_facility.py
sdwis_drink_water/sdwis_drink_water.py
sdwis_drink_water/utils.py
sdwis_drink_water/utils_for_jupyter_print.py
sdwis_drink_water-1.1.2.dist-info/LICENSE
sdwis_drink_water-1.1.2.dist-info/METADATA
sdwis_drink_water-1.1.2.dist-info/WHEEL
sdwis_drink_water-1.1.2.dist-info/RECORD
