Metadata-Version: 2.1
Name: sdwis_drink_water
Version: 1.1.2
Summary: Python wrappers for the Envirofacts Data Service API provided by the U.S. Environmental Protection Agency (EPA), with a focus on the Safe Drinking Water Information System (SDWIS).
License: MIT
Author: norahtao
Requires-Python: >=3.9,<4.0
Classifier: License :: OSI Approved :: MIT License
Classifier: Programming Language :: Python :: 3
Classifier: Programming Language :: Python :: 3.9
Classifier: Programming Language :: Python :: 3.10
Classifier: Programming Language :: Python :: 3.11
Classifier: Programming Language :: Python :: 3.12
Requires-Dist: beautifulsoup4 (>=4.12.2,<5.0.0)
Requires-Dist: pandas (>=2.1.4,<3.0.0)
Requires-Dist: requests (>=2.31.0,<3.0.0)
Requires-Dist: requests-cache (>=1.1.1,<2.0.0)
Requires-Dist: setuptools (>=69.0.2,<70.0.0)
Requires-Dist: tabulate (>=0.9.0,<0.10.0)
Requires-Dist: tqdm (>=4.66.1,<5.0.0)
